sdk/__init__.py
sdk/comm/__init__.py
sdk/comm/client_connector.py
sdk/comm/gcm_crypto_helper.py
sdk/comm/key_parser_helper.py
sdk/comm/message_codec.py
sdk/comm/socket_helper.py
sdk/comm/ssl_helper.py
sdk/command/__init__.py
sdk/command/command_base.py
sdk/command/command_interface.py
sdk/command/command_type.py
sdk/command/impl/__init__.py
sdk/command/impl/del_command.py
sdk/command/impl/get_command.py
sdk/command/impl/get_secondary_idx_one_command.py
sdk/command/impl/get_secondary_idx_two_command.py
sdk/command/impl/ping_command.py
sdk/command/impl/set_command.py
sdk/model/__init__.py
sdk/model/client_option.py
sdk/model/command_result.py
sdk/model/encryption_mode.py
sdk/model/get_result.py
sdk/model/vertex_cache_sdk_exception.py
sdk/vertexcache_sdk.py
vertexcache_sdk-1.0.0.dist-info/METADATA
vertexcache_sdk-1.0.0.dist-info/WHEEL
vertexcache_sdk-1.0.0.dist-info/RECORD
