Metadata-Version: 2.3
Name: vertexcache-sdk
Version: 1.0.0
Summary: Official Python Client SDK for VertexCache
License: Apache-2.0
Keywords: vertexcache,cache,sdk,client
Author: Jason Lam
Requires-Python: >=3.9,<4.0
Classifier: License :: OSI Approved :: Apache Software License
Classifier: Programming Language :: Python :: 3
Classifier: Programming Language :: Python :: 3.9
Classifier: Programming Language :: Python :: 3.10
Classifier: Programming Language :: Python :: 3.11
Classifier: Programming Language :: Python :: 3.12
Classifier: Programming Language :: Python :: 3.13
Requires-Dist: cryptography (>=45.0.3) ; python_version != "3.9.0" and python_version != "3.9.1"
Project-URL: Documentation, https://vertexcache.com/docs
Project-URL: Homepage, https://github.com/VertexCache/VertexCache
Project-URL: Repository, https://github.com/VertexCache/VertexCache/tree/main/client-sdks/python
